setup.py
termcolor2.py
termcolor2.egg-info/PKG-INFO
termcolor2.egg-info/SOURCES.txt
termcolor2.egg-info/dependency_links.txt
termcolor2.egg-info/top_level.txt