Metadata-Version: 1.1
Name: termcolor2
Version: 0.0.2
Summary: simple termcolor wrapper
Home-page: https://github.com/v2e4lisp/termcolor2
Author: Yan Wenjun
Author-email: mylastnameisyan@gmail.com
License: MIT
Platform: UNKNOWN
Requires: termcolor
